jsondatafaker/__init__.py
jsondatafaker/cli.py
jsondatafaker/config.py
jsondatafaker/jsondatafaker.py
jsondatafaker/util.py
jsondatafaker-1.0.1.dist-info/LICENSE
jsondatafaker-1.0.1.dist-info/LICENSE copy
jsondatafaker-1.0.1.dist-info/METADATA
jsondatafaker-1.0.1.dist-info/WHEEL
jsondatafaker-1.0.1.dist-info/entry_points.txt
jsondatafaker-1.0.1.dist-info/top_level.txt
jsondatafaker-1.0.1.dist-info/RECORD
