Metadata-Version: 2.1
Name: jsondatafaker
Version: 1.0.1
Summary: Generate and Save Fake JSON defining the schema with Yaml
Author: Necati Arslan
Author-email: necatia@gmail.com
Project-URL: Documentation, https://github.com/necatiarslan/json-datafaker/blob/main/README.md
Project-URL: Source, https://github.com/necatiarslan/json-datafaker
Classifier: Development Status :: 5 - Production/Stable
Classifier: Intended Audience :: Developers
Classifier: License :: OSI Approved :: Apache Software License
Classifier: Programming Language :: Python
Classifier: Programming Language :: Python :: 3
Classifier: Programming Language :: Python :: 3.7
Classifier: Programming Language :: Python :: 3.8
Classifier: Programming Language :: Python :: 3.9
Classifier: Programming Language :: Python :: 3.10
Classifier: Programming Language :: Python :: 3.11
Classifier: Programming Language :: Python :: 3.12
Classifier: Topic :: Software Development :: Libraries
License-File: LICENSE
License-File: LICENSE copy
Requires-Dist: faker
Requires-Dist: pyyaml
